quotespy/__init__.py
quotespy/graphics/__init__.py
quotespy/graphics/graphics.py
quotespy/graphics/tools/__init__.py
quotespy/graphics/tools/default_settings.py
quotespy/graphics/tools/errors.py
quotespy/graphics/tools/type_interfaces.py
quotespy/graphics/tools/utils.py
quotespy/graphics/tools/validation.py
quotespy/tweet_graphics/__init__.py
quotespy/tweet_graphics/tweet_graphics.py
quotespy/tweet_graphics/tools/__init__.py
quotespy/tweet_graphics/tools/default_settings.py
quotespy/tweet_graphics/tools/errors.py
quotespy/tweet_graphics/tools/type_interfaces.py
quotespy/tweet_graphics/tools/utils.py
quotespy/tweet_graphics/tools/validation.py
quotespy-1.3.dist-info/LICENSE
quotespy-1.3.dist-info/METADATA
quotespy-1.3.dist-info/WHEEL
quotespy-1.3.dist-info/top_level.txt
quotespy-1.3.dist-info/RECORD
