Metadata-Version: 2.1
Name: quotespy
Version: 1.3
Summary: Python library to create quotes/lyrics and tweet graphics with PIL.
Home-page: https://github.com/Ze1598/quotespy
Author: Jose Costa
Author-email: jose.fernando.costa.1998@gmail.com
License: UNKNOWN
Platform: UNKNOWN
Classifier: Programming Language :: Python :: 3
Classifier: Development Status :: 5 - Production/Stable
Classifier: Operating System :: Microsoft :: Windows :: Windows 10
Requires-Python: >=3.7
Requires-Dist: pillow (>=7.1.2)
Requires-Dist: typing-extensions (>=3.7.4.2)
